damnpth-0.1.dist-info/METADATA
damnpth-0.1.dist-info/WHEEL
damnpth-0.1.dist-info/entry_points.txt
damnpth/__init__.py
damnpth-0.1.dist-info/RECORD
