Metadata-Version: 1.2
Name: damnpth
Version: 0.1
Summary: Forcibly fix .pth files made by setuptools
Home-page: https://github.com/takluyver/damnpth
License: UNKNOWN
Author: Thomas Kluyver
Author-email: thomas@kluyver.me.uk
Classifier: License :: OSI Approved :: MIT License
Requires-Dist: astcheck
